bondai/__init__.py
bondai/main.py
bondai/agents/__init__.py
bondai/agents/agent.py
bondai/agents/conversation_member.py
bondai/agents/conversational_agent.py
bondai/agents/messages.py
bondai/agents/util.py
bondai/agents/compression/__init__.py
bondai/agents/compression/conversation_summarizer.py
bondai/agents/compression/message_summarizer.py
bondai/agents/compression/prompts/conversation_summarizer_prompt_template.md
bondai/agents/compression/prompts/message_summarizer_prompt_template.md
bondai/agents/group_chat/__init__.py
bondai/agents/group_chat/group_conversation.py
bondai/agents/group_chat/group_conversation_config.py
bondai/agents/group_chat/user_proxy.py
bondai/agents/prompts/__init__.py
bondai/agents/prompts/agent_message_prompt_template.md
bondai/agents/prompts/conversational_agent_system_prompt_template.md
bondai/agents/prompts/default_persona.py
bondai/agents/prompts/react_agent_system_prompt_template.md
bondai/api/__init__.py
bondai/api/agent_wrapper.py
bondai/api/api_error.py
bondai/api/api_user_proxy.py
bondai/api/client.py
bondai/api/routes.py
bondai/api/server.py
bondai/api/settings.py
bondai/cli/__init__.py
bondai/cli/cli.py
bondai/cli/default_tools.py
bondai/cli/personas/__init__.py
bondai/cli/personas/user_liaison_agent.py
bondai/memory/__init__.py
bondai/memory/memory_manager.py
bondai/memory/archival/__init__.py
bondai/memory/archival/datasources.py
bondai/memory/archival/tools.py
bondai/memory/conversation/__init__.py
bondai/memory/conversation/datasources.py
bondai/memory/conversation/tools.py
bondai/memory/core/__init__.py
bondai/memory/core/datasources.py
bondai/memory/core/tools.py
bondai/memory/prompts/default_prompt_template.md
bondai/models/__init__.py
bondai/models/embedding_model.py
bondai/models/llm.py
bondai/models/openai/__init__.py
bondai/models/openai/default_openai_connection_params.py
bondai/models/openai/env_vars.py
bondai/models/openai/openai_connection_params.py
bondai/models/openai/openai_embedding_model.py
bondai-0.3.1.dist-info/LICENSE
bondai-0.3.1.dist-info/METADATA
bondai-0.3.1.dist-info/WHEEL
bondai-0.3.1.dist-info/entry_points.txt
bondai-0.3.1.dist-info/top_level.txt
bondai-0.3.1.dist-info/RECORD
