Metadata-Version: 2.1
Name: bondai
Version: 0.3.1
Summary: An AI-powered console assistant with a versatile API for seamless integration into applications.
Home-page: https://bondai.dev
Author: Kevin Rohling
Author-email: kevin@kevinrohling.com
Classifier: Development Status :: 3 - Alpha
Classifier: Intended Audience :: Developers
Classifier: Programming Language :: Python :: 3.10
Classifier: License :: OSI Approved :: MIT License
License-File: LICENSE
Requires-Dist: aiofiles ==23.2.1
Requires-Dist: aiohttp ==3.8.5
Requires-Dist: aiosignal ==1.3.1
Requires-Dist: alpaca-py ==0.13.4
Requires-Dist: aniso8601 ==9.0.1
Requires-Dist: annotated-types ==0.5.0
Requires-Dist: anyio ==3.7.1
Requires-Dist: appdirs ==1.4.4
Requires-Dist: async-timeout ==4.0.3
Requires-Dist: asyncio ==3.4.3
Requires-Dist: attrs ==23.1.0
Requires-Dist: beautifulsoup4 ==4.12.2
Requires-Dist: bidict ==0.22.1
Requires-Dist: blinker ==1.6.2
Requires-Dist: Brotli ==1.1.0
Requires-Dist: bs4 ==0.0.1
Requires-Dist: cachetools ==5.3.1
Requires-Dist: certifi ==2023.11.17
Requires-Dist: charset-normalizer ==3.2.0
Requires-Dist: click ==8.1.7
Requires-Dist: cssselect ==1.2.0
Requires-Dist: distro ==1.8.0
Requires-Dist: duckduckgo-search ==4.2.0
Requires-Dist: faiss-cpu ==1.7.4
Requires-Dist: fake-useragent ==1.2.1
Requires-Dist: Flask ==3.0.0
Requires-Dist: Flask-Cors ==4.0.0
Requires-Dist: Flask-RESTful ==0.3.10
Requires-Dist: Flask-SocketIO ==5.3.6
Requires-Dist: frozenlist ==1.4.0
Requires-Dist: google-api-core ==2.11.1
Requires-Dist: google-api-python-client ==2.97.0
Requires-Dist: google-auth ==2.25.2
Requires-Dist: google-auth-httplib2 ==0.2.0
Requires-Dist: googleapis-common-protos ==1.60.0
Requires-Dist: h11 ==0.14.0
Requires-Dist: h2 ==3.2.0
Requires-Dist: hpack ==3.0.0
Requires-Dist: httpcore ==1.0.2
Requires-Dist: httplib2 ==0.22.0
Requires-Dist: hyperframe ==5.2.0
Requires-Dist: idna ==3.4
Requires-Dist: importlib-metadata ==6.8.0
Requires-Dist: itsdangerous ==2.1.2
Requires-Dist: Jinja2 ==3.1.2
Requires-Dist: joblib ==1.3.2
Requires-Dist: lxml ==4.9.3
Requires-Dist: MarkupSafe ==2.1.3
Requires-Dist: msgpack ==1.0.5
Requires-Dist: multidict ==6.0.4
Requires-Dist: nltk ==3.8.1
Requires-Dist: numpy ==1.25.2
Requires-Dist: openai ==1.3.3
Requires-Dist: packaging ==23.2
Requires-Dist: pandas ==2.0.3
Requires-Dist: parse ==1.19.1
Requires-Dist: pre-commit ==3.6.0
Requires-Dist: protobuf ==4.24.1
Requires-Dist: psycopg2-binary ==2.9.7
Requires-Dist: pyasn1 ==0.5.0
Requires-Dist: pyasn1-modules ==0.3.0
Requires-Dist: pydantic ==2.4.2
Requires-Dist: pyee ==8.2.2
Requires-Dist: pyparsing ==3.1.1
Requires-Dist: PyPDF2 ==3.0.1
Requires-Dist: pyquery ==2.0.0
Requires-Dist: python-dateutil ==2.8.2
Requires-Dist: python-docx ==1.1.0
Requires-Dist: python-engineio ==4.7.1
Requires-Dist: python-socketio ==5.9.0
Requires-Dist: pytz ==2023.3
Requires-Dist: regex ==2023.8.8
Requires-Dist: requests ==2.31.0
Requires-Dist: requests-html ==0.10.0
Requires-Dist: rfc3986 ==1.5.0
Requires-Dist: rsa ==4.9
Requires-Dist: simple-websocket ==1.0.0
Requires-Dist: six ==1.16.0
Requires-Dist: sniffio ==1.3.0
Requires-Dist: socksio ==1.0.0
Requires-Dist: soupsieve ==2.4.1
Requires-Dist: sseclient-py ==1.7.2
Requires-Dist: termcolor ==2.3.0
Requires-Dist: tiktoken ==0.4.0
Requires-Dist: tqdm ==4.66.1
Requires-Dist: typing-extensions ==4.6.1
Requires-Dist: tzdata ==2023.3
Requires-Dist: uritemplate ==4.1.1
Requires-Dist: urllib3 ==2.0.7
Requires-Dist: w3lib ==2.1.2
Requires-Dist: websocket-client ==1.6.3
Requires-Dist: websockets ==11.0.3
Requires-Dist: wsproto ==1.2.0
Requires-Dist: yarl ==1.9.2
Requires-Dist: zipp ==3.16.2
